more_metrics/__init__.py
more_metrics/more_metrics.py
more_metrics-0.11.0.dist-info/licenses/LICENSE
more_metrics-0.11.0.dist-info/METADATA
more_metrics-0.11.0.dist-info/WHEEL
more_metrics-0.11.0.dist-info/top_level.txt
more_metrics-0.11.0.dist-info/RECORD
