Metadata-Version: 2.4
Name: more_metrics
Version: 0.11.0
Summary: A Python package for computing additional classification metrics for machine learning or AI models. These metrics include and also known as AUC, NRI, and IDI
Home-page: https://github.com/LambertLeong/AUC_NRI_IDI_python_functions
Author: Lambert T Leong
Author-email: lamberttleong@gmail.com
License: GPL-3.0
Classifier: Programming Language :: Python :: 3
Classifier: License :: OSI Approved :: GNU General Public License v3 (GPLv3)
Classifier: Operating System :: OS Independent
Requires-Python: >=3.6
License-File: LICENSE
Requires-Dist: numpy
Requires-Dist: scikit-learn
Requires-Dist: matplotlib
Dynamic: author
Dynamic: author-email
Dynamic: classifier
Dynamic: description
Dynamic: description-content-type
Dynamic: home-page
Dynamic: license
Dynamic: license-file
Dynamic: requires-dist
Dynamic: requires-python
Dynamic: summary
